converter/__init__.py
converter/cli.py
converter/converter.py
converter/errors.py
converter/tests/__snapshots__/test_converter/test_air_quality.json
converter/tests/__snapshots__/test_converter/test_company_basic_info_errors.json
converter/tests/__snapshots__/test_converter/test_current_weather_required_headers.json
converter/tests/__snapshots__/test_converter/test_teapot_deprecated.json
converter/tests/conftest.py
converter/tests/data/AirQuality/Current.py
converter/tests/data/Appliance/CoffeeBrewer.py
converter/tests/data/Company/BasicInfo.py
converter/tests/data/Weather/Current/Metric.py
converter/tests/test_converter.py
data_product_definition_tooling-0.0.13.dist-info/LICENSE
data_product_definition_tooling-0.0.13.dist-info/METADATA
data_product_definition_tooling-0.0.13.dist-info/WHEEL
data_product_definition_tooling-0.0.13.dist-info/entry_points.txt
data_product_definition_tooling-0.0.13.dist-info/RECORD
