Metadata-Version: 2.1
Name: data-product-definition-tooling
Version: 0.0.13
Summary: Data Product Definition Tooling
Home-page: https://github.com/ioxio-dataspace/data-product-definition-tooling
License: BSD-3-Clause
Author: IOXIO Ltd
Requires-Python: >=3.9.0,<4
Classifier: License :: OSI Approved :: BSD License
Classifier: Programming Language :: Python :: 3
Classifier: Programming Language :: Python :: 3.9
Classifier: Programming Language :: Python :: 3.10
Classifier: Programming Language :: Python :: 3.11
Requires-Dist: deepdiff (>=6.3.0,<7.0.0)
Requires-Dist: fastapi (>=0.96.0,<0.97.0)
Requires-Dist: pydantic[email] (>=1.10.8,<2.0.0)
Requires-Dist: stringcase (>=1.2.0,<2.0.0)
Requires-Dist: typer[all] (>=0.9.0,<0.10.0)
Project-URL: Repository, https://github.com/ioxio-dataspace/data-product-definition-tooling
